{
  "success": true,
  "body": {
    "id": "glavnaya-studiynaya-devushki-dasha",
    "level": 3,
    "name": "Даша",
    "date": "2018-10-22T12:18:27.000Z",
    "breadcrumbs": [
      {
        "id": "glavnaya",
        "name": "Главная"
      },
      {
        "id": "glavnaya-studiynaya",
        "name": "Студийная"
      },
      {
        "id": "glavnaya-studiynaya-devushki",
        "name": "Девушки"
      },
      {
        "id": "glavnaya-studiynaya-devushki-dasha",
        "name": "Даша"
      }
    ],
    "albums": [],
    "photos": [
      {
        "id": 116,
        "url": {
          "original": "images\\original\\af8df-dasha\\1.jpg",
          "preview": "images\\preview\\af8df-dasha\\1.jpg"
        },
        "name": "1.jpg",
        "isCover": false
      },
      {
        "id": 117,
        "url": {
          "original": "images\\original\\af8df-dasha\\10.jpg",
          "preview": "images\\preview\\af8df-dasha\\10.jpg"
        },
        "name": "10.jpg",
        "isCover": false
      },
      {
        "id": 118,
        "url": {
          "original": "images\\original\\af8df-dasha\\11.jpg",
          "preview": "images\\preview\\af8df-dasha\\11.jpg"
        },
        "name": "11.jpg",
        "isCover": false
      },
      {
        "id": 119,
        "url": {
          "original": "images\\original\\af8df-dasha\\2.jpg",
          "preview": "images\\preview\\af8df-dasha\\2.jpg"
        },
        "name": "2.jpg",
        "isCover": false
      },
      {
        "id": 120,
        "url": {
          "original": "images\\original\\af8df-dasha\\3.jpg",
          "preview": "images\\preview\\af8df-dasha\\3.jpg"
        },
        "name": "3.jpg",
        "isCover": false
      },
      {
        "id": 121,
        "url": {
          "original": "images\\original\\af8df-dasha\\4.jpg",
          "preview": "images\\preview\\af8df-dasha\\4.jpg"
        },
        "name": "4.jpg",
        "isCover": false
      },
      {
        "id": 122,
        "url": {
          "original": "images\\original\\af8df-dasha\\5.jpg",
          "preview": "images\\preview\\af8df-dasha\\5.jpg"
        },
        "name": "5.jpg",
        "isCover": false
      },
      {
        "id": 123,
        "url": {
          "original": "images\\original\\af8df-dasha\\7.jpg",
          "preview": "images\\preview\\af8df-dasha\\7.jpg"
        },
        "name": "7.jpg",
        "isCover": false
      },
      {
        "id": 124,
        "url": {
          "original": "images\\original\\af8df-dasha\\6.jpg",
          "preview": "images\\preview\\af8df-dasha\\6.jpg"
        },
        "name": "6.jpg",
        "isCover": false
      },
      {
        "id": 125,
        "url": {
          "original": "images\\original\\af8df-dasha\\8.jpg",
          "preview": "images\\preview\\af8df-dasha\\8.jpg"
        },
        "name": "8.jpg",
        "isCover": false
      },
      {
        "id": 126,
        "url": {
          "original": "images\\original\\af8df-dasha\\9.jpg",
          "preview": "images\\preview\\af8df-dasha\\9.jpg"
        },
        "name": "9.jpg",
        "isCover": false
      },
      {
        "id": 127,
        "url": {
          "original": "images\\original\\af8df-dasha\\oblozhka.jpg",
          "preview": "images\\preview\\af8df-dasha\\oblozhka.jpg"
        },
        "name": "oblozhka.jpg",
        "isCover": true
      }
    ]
  }
}